margaritashotgun/__init__.py
margaritashotgun/auth.py
margaritashotgun/cli.py
margaritashotgun/client.py
margaritashotgun/exceptions.py
margaritashotgun/logger.py
margaritashotgun/memory.py
margaritashotgun/remote_host.py
margaritashotgun/remote_shell.py
margaritashotgun/repository.py
margaritashotgun/settings.py
margaritashotgun/ssh_tunnel.py
margaritashotgun/workers.py
margaritashotgun/util/__init__.py
margaritashotgun/util/parser.py
margaritashotgun-0.4.1.data/scripts/margaritashotgun
margaritashotgun-0.4.1.dist-info/DESCRIPTION.rst
margaritashotgun-0.4.1.dist-info/METADATA
margaritashotgun-0.4.1.dist-info/RECORD
margaritashotgun-0.4.1.dist-info/WHEEL
margaritashotgun-0.4.1.dist-info/metadata.json
margaritashotgun-0.4.1.dist-info/top_level.txt
