Metadata-Version: 2.0
Name: margaritashotgun
Version: 0.4.1
Summary: Remote memory aquisition wrapper for LiME
Home-page: https://github.com/ThreatResponse/margaritashotgun
Author: Joel Ferrier
Author-email: joel@ferrier.io
License: MIT
Download-URL: https://github.com/ThreatResponse/margaritashotgun/archive/v0.4.1.tar.gz
Platform: UNKNOWN
Requires-Dist: boto3 (>=1.3.0)
Requires-Dist: enum34
Requires-Dist: logutils (==0.3.3)
Requires-Dist: paramiko (>=1.16.0)
Requires-Dist: progressbar-latest
Requires-Dist: prompt-toolkit
Requires-Dist: python-decouple
Requires-Dist: python-gnupg (==0.3.9)
Requires-Dist: pyyaml (>=3.11)
Requires-Dist: requests
Requires-Dist: s3fs (>=0.0.2)
Requires-Dist: xmltodict
